{
  "active": false,
  "category": null,
  "description": null,
  "device_type": "browser",
  "hint": null,
  "name": "problem_management",
  "order": 300,
  "roles": "itil,problem_task_analyst",
  "sys_class_name": "sys_app_application",
  "sys_created_by": "pat",
  "sys_created_on": "2004-07-20 23:40:18",
  "sys_id": "deed4a24c6112287013cba41a9e205ca",
  "sys_mod_count": 12,
  "sys_name": "Problem",
  "sys_package": "aa62bdf113932300aee432228144b011",
  "sys_policy": null,
  "sys_scope": "global",
  "sys_update_name": "sys_app_application_deed4a24c6112287013cba41a9e205ca",
  "sys_updated_by": "admin",
  "sys_updated_on": "2019-05-31 14:10:41",
  "title": "Problem",
  "view_name": null
}
